{
	"version": "V000001",
	"size": [500, 500],
	"nodes": [
		{
			"type": "Rectangle",
			"visible": true,
			"size": [50, 50],
			"translation": [25, 25],
			"rotationDeg": 2.4848083448933725e-17,
			"cornerRadii": [0, 0, 0, 0],
			"blendMode": "Normal",
			"opacity": 1,
			"layoutElement": {
				"type": "Absolute",
				"constraints": { "horizontal": "Center", "vertical": "Center" }
			},
			"styles": [
				{
					"type": "Fill",
					"paintId": { "type": "ReferenceId", "referenceId": "p4" },
					"blendMode": "Normal",
					"opacity": 1,
					"visible": true
				}
			],
			"id": "n3"
		},
		{
			"type": "Frame",
			"clipContent": false,
			"layoutParent": null,
			"visible": true,
			"children": [{ "type": "ReferenceId", "referenceId": "n3" }],
			"size": [100, 100],
			"translation": [200, 100],
			"rotationDeg": 0,
			"cornerRadii": [0, 0, 0, 0],
			"blendMode": "Normal",
			"opacity": 1,
			"layoutElement": {
				"type": "Absolute",
				"constraints": { "horizontal": "Start", "vertical": "Start" }
			},
			"styles": [
				{
					"type": "Fill",
					"paintId": { "type": "ReferenceId", "referenceId": "p5" },
					"blendMode": "Normal",
					"opacity": 1,
					"visible": true
				}
			],
			"id": "n2"
		},
		{
			"type": "Rectangle",
			"visible": true,
			"size": [50, 50],
			"translation": [25.000057220458984, 25.00000762939453],
			"rotationDeg": 2.4848083448933725e-17,
			"cornerRadii": [0, 0, 0, 0],
			"blendMode": "Normal",
			"opacity": 1,
			"layoutElement": {
				"type": "Absolute",
				"constraints": { "horizontal": "Start", "vertical": "Start" }
			},
			"styles": [
				{
					"type": "Fill",
					"paintId": { "type": "ReferenceId", "referenceId": "p4" },
					"blendMode": "Normal",
					"opacity": 1,
					"visible": true
				}
			],
			"id": "n7"
		},
		{
			"type": "Frame",
			"clipContent": false,
			"layoutParent": null,
			"visible": true,
			"children": [{ "type": "ReferenceId", "referenceId": "n7" }],
			"size": [100, 100],
			"translation": [200, 0],
			"rotationDeg": 0,
			"cornerRadii": [0, 0, 0, 0],
			"blendMode": "Normal",
			"opacity": 1,
			"layoutElement": {
				"type": "Absolute",
				"constraints": { "horizontal": "Start", "vertical": "Start" }
			},
			"styles": [
				{
					"type": "Fill",
					"paintId": { "type": "ReferenceId", "referenceId": "p5" },
					"blendMode": "Normal",
					"opacity": 1,
					"visible": true
				}
			],
			"id": "n6"
		},
		{
			"type": "Rectangle",
			"visible": true,
			"size": [50, 50],
			"translation": [25.000057220458984, 25.00000762939453],
			"rotationDeg": 2.4848083448933725e-17,
			"cornerRadii": [0, 0, 0, 0],
			"blendMode": "Normal",
			"opacity": 1,
			"layoutElement": {
				"type": "Absolute",
				"constraints": { "horizontal": "End", "vertical": "End" }
			},
			"styles": [
				{
					"type": "Fill",
					"paintId": { "type": "ReferenceId", "referenceId": "p4" },
					"blendMode": "Normal",
					"opacity": 1,
					"visible": true
				}
			],
			"id": "n9"
		},
		{
			"type": "Frame",
			"clipContent": false,
			"layoutParent": null,
			"visible": true,
			"children": [{ "type": "ReferenceId", "referenceId": "n9" }],
			"size": [100, 100],
			"translation": [200, 200],
			"rotationDeg": 0,
			"cornerRadii": [0, 0, 0, 0],
			"blendMode": "Normal",
			"opacity": 1,
			"layoutElement": {
				"type": "Absolute",
				"constraints": { "horizontal": "Start", "vertical": "Start" }
			},
			"styles": [
				{
					"type": "Fill",
					"paintId": { "type": "ReferenceId", "referenceId": "p5" },
					"blendMode": "Normal",
					"opacity": 1,
					"visible": true
				}
			],
			"id": "n8"
		},
		{
			"type": "Rectangle",
			"visible": true,
			"size": [50, 50],
			"translation": [25.000057220458984, 25.00000762939453],
			"rotationDeg": 2.4848083448933725e-17,
			"cornerRadii": [0, 0, 0, 0],
			"blendMode": "Normal",
			"opacity": 1,
			"layoutElement": {
				"type": "Absolute",
				"constraints": { "horizontal": "Stretch", "vertical": "Stretch" }
			},
			"styles": [
				{
					"type": "Fill",
					"paintId": { "type": "ReferenceId", "referenceId": "p4" },
					"blendMode": "Normal",
					"opacity": 1,
					"visible": true
				}
			],
			"id": "n11"
		},
		{
			"type": "Frame",
			"clipContent": false,
			"layoutParent": null,
			"visible": true,
			"children": [{ "type": "ReferenceId", "referenceId": "n11" }],
			"size": [100, 100],
			"translation": [200, 300],
			"rotationDeg": 0,
			"cornerRadii": [0, 0, 0, 0],
			"blendMode": "Normal",
			"opacity": 1,
			"layoutElement": {
				"type": "Absolute",
				"constraints": { "horizontal": "Start", "vertical": "Start" }
			},
			"styles": [
				{
					"type": "Fill",
					"paintId": { "type": "ReferenceId", "referenceId": "p5" },
					"blendMode": "Normal",
					"opacity": 1,
					"visible": true
				}
			],
			"id": "n10"
		},
		{
			"type": "Rectangle",
			"visible": true,
			"size": [50, 50],
			"translation": [25.000057220458984, 25.00000762939453],
			"rotationDeg": 2.4848083448933725e-17,
			"cornerRadii": [0, 0, 0, 0],
			"blendMode": "Normal",
			"opacity": 1,
			"layoutElement": {
				"type": "Absolute",
				"constraints": { "horizontal": "Scale", "vertical": "Scale" }
			},
			"styles": [
				{
					"type": "Fill",
					"paintId": { "type": "ReferenceId", "referenceId": "p4" },
					"blendMode": "Normal",
					"opacity": 1,
					"visible": true
				}
			],
			"id": "n13"
		},
		{
			"type": "Frame",
			"clipContent": false,
			"layoutParent": null,
			"visible": true,
			"children": [{ "type": "ReferenceId", "referenceId": "n13" }],
			"size": [100, 100],
			"translation": [200, 400],
			"rotationDeg": 0,
			"cornerRadii": [0, 0, 0, 0],
			"blendMode": "Normal",
			"opacity": 1,
			"layoutElement": {
				"type": "Absolute",
				"constraints": { "horizontal": "Start", "vertical": "Start" }
			},
			"styles": [
				{
					"type": "Fill",
					"paintId": { "type": "ReferenceId", "referenceId": "p5" },
					"blendMode": "Normal",
					"opacity": 1,
					"visible": true
				}
			],
			"id": "n12"
		},
		{
			"type": "Frame",
			"clipContent": false,
			"layoutParent": null,
			"visible": true,
			"children": [
				{ "type": "ReferenceId", "referenceId": "n12" },
				{ "type": "ReferenceId", "referenceId": "n10" },
				{ "type": "ReferenceId", "referenceId": "n8" },
				{ "type": "ReferenceId", "referenceId": "n6" },
				{ "type": "ReferenceId", "referenceId": "n2" }
			],
			"size": [500, 500],
			"translation": [0, 0],
			"rotationDeg": 0,
			"cornerRadii": [0, 0, 0, 0],
			"blendMode": "Normal",
			"opacity": 1,
			"layoutElement": {
				"type": "Absolute",
				"constraints": { "horizontal": "Start", "vertical": "Start" }
			},
			"styles": [
				{
					"type": "Fill",
					"paintId": { "type": "ReferenceId", "referenceId": "p14" },
					"blendMode": "Normal",
					"opacity": 1,
					"visible": true
				}
			],
			"id": "n1"
		}
	],
	"paints": [
		{ "type": "Solid", "color": [217, 217, 217], "id": "p4" },
		{ "type": "Solid", "color": [243, 6, 6], "id": "p5" },
		{ "type": "Solid", "color": [255, 248, 78], "id": "p14" }
	],
	"assets": [],
	"viewport": { "physicalPosition": [0, 0], "physicalSize": [500, 500] }
}
