{
	"openapi": "3.0.3",
	"info": {
		"title": "Composition Render API",
		"description": "todo",
		"contact": { "name": "dyn.art", "url": "https://dyn.art/?source=apidocs" },
		"license": { "name": "AGPL-3.0-or-later" },
		"version": "1.0.0"
	},
	"paths": {
		"/v1/render": {
			"post": {
				"tags": ["crate::routes::v1::render::controller"],
				"operationId": "render_composition",
				"parameters": [
					{ "name": "format", "in": "path", "required": true, "schema": { "type": "string" } }
				],
				"requestBody": {
					"description": "",
					"content": {
						"application/json": {
							"schema": {
								"allOf": [{ "$ref": "#/components/schemas/DTIFComposition" }],
								"nullable": true
							}
						}
					},
					"required": false
				},
				"responses": {
					"200": {
						"description": "Generation success",
						"content": {
							"application/json": { "schema": { "$ref": "#/components/schemas/DTIFComposition" } }
						}
					},
					"400": { "description": "Bad Request" }
				}
			}
		}
	}
}
